{
  "project_info": {
    "project_number": "586707241879",
    "firebase_url": "https://flash-chat-696.firebaseio.com",
    "project_id": "flash-chat-696",
    "storage_bucket": "flash-chat-696.appspot.com"
  },
  "client": [
    {
      "client_info": {
        "mobilesdk_app_id": "1:586707241879:android:d2829c1242119609",
        "android_client_info": {
          "package_name": "com.japronto.flash_chat"
        }
      },
      "oauth_client": [
        {
          "client_id": "586707241879-snbqaom3vuud05l9ur8k87he6de17os9.apps.googleusercontent.com",
          "client_type": 3
        }
      ],
      "api_key": [
        {
          "current_key": "AIzaSyBmTPSDivdZ9KJH4qi3f_G8Pft7mlyiBdk"
        }
      ],
      "services": {
        "appinvite_service": {
          "other_platform_oauth_client": [
            {
              "client_id": "586707241879-snbqaom3vuud05l9ur8k87he6de17os9.apps.googleusercontent.com",
              "client_type": 3
            }
          ]
        }
      }
    }
  ],
  "configuration_version": "1"
}